README.md
setup.py
hgflask/client.py
hgflask/httpfs.py
hgflask/server.py
hgflask/tilesets.py
hgflask.egg-info/PKG-INFO
hgflask.egg-info/SOURCES.txt
hgflask.egg-info/dependency_links.txt
hgflask.egg-info/requires.txt
hgflask.egg-info/top_level.txt