Metadata-Version: 1.0
Name: hgflask
Version: 0.1.2
Summary: Portable higlass tile server
Home-page: UNKNOWN
Author: Nezar Abdennur, Peter Kerpedjiev
Author-email: nabdennur@gmail.com
License: UNKNOWN
Platform: UNKNOWN
